sklearn_compat/__init__.py
sklearn_compat/_sklearn_compat.py
sklearn_compat/base.py
sklearn_compat/utils/__init__.py
sklearn_compat/utils/_chunking.py
sklearn_compat/utils/_indexing.py
sklearn_compat/utils/_mask.py
sklearn_compat/utils/_missing.py
sklearn_compat/utils/_optional_dependencies.py
sklearn_compat/utils/_param_validation.py
sklearn_compat/utils/_tags.py
sklearn_compat/utils/_user_interface.py
sklearn_compat/utils/estimator_checks.py
sklearn_compat/utils/extmath.py
sklearn_compat/utils/fixes.py
sklearn_compat/utils/metadata_routing.py
sklearn_compat/utils/multiclass.py
sklearn_compat/utils/validation.py
sklearn_compat/utils/_test_common/instance_generator.py
sklearn_compat-0.1.2.dist-info/METADATA
sklearn_compat-0.1.2.dist-info/WHEEL
sklearn_compat-0.1.2.dist-info/licenses/LICENSE
sklearn_compat-0.1.2.dist-info/RECORD
