Metadata-Version: 2.4
Name: sklearn-compat
Version: 0.1.2
Summary: Ease support for compatible scikit-learn estimators across versions
Project-URL: Homepage, https://sklearn-compat.readthedocs.io/en/
Project-URL: Source, https://github.com/sklearn-compat/sklearn-compat
Project-URL: Issues, https://github.com/sklearn-compat/sklearn-compat/issues
Author-email: Guillaume Lemaitre <guillaume@probabl.ai>, Adrin Jalali <adrin.jalali@gmail.com>
License-File: LICENSE
Classifier: Development Status :: 4 - Beta
Classifier: License :: OSI Approved :: BSD License
Classifier: Programming Language :: Python :: 3 :: Only
Classifier: Programming Language :: Python :: 3.8
Classifier: Programming Language :: Python :: 3.9
Classifier: Programming Language :: Python :: 3.10
Classifier: Programming Language :: Python :: 3.11
Classifier: Programming Language :: Python :: 3.12
Classifier: Programming Language :: Python :: 3.13
Classifier: Topic :: Scientific/Engineering :: Physics
Requires-Python: >=3.8
Requires-Dist: scikit-learn<1.7,>=1.2
Provides-Extra: dev
Requires-Dist: ipython; extra == 'dev'
Provides-Extra: docs
Requires-Dist: mkdocs; extra == 'docs'
Requires-Dist: mkdocs-material; extra == 'docs'
Provides-Extra: lint
Requires-Dist: pre-commit; extra == 'lint'
Provides-Extra: tests
Requires-Dist: pandas; extra == 'tests'
Requires-Dist: pytest; extra == 'tests'
Requires-Dist: pytest-cov; extra == 'tests'
Requires-Dist: pytest-xdist; extra == 'tests'
Requires-Dist: pytz; extra == 'tests'
